[
  {
    "title": "Structure",
    "description": null,
    "source": "https://github.com/shubhamjha2510/Structure",
    "demo": "",
    "language": null,
    "platform": "github",
    "createdAt": "2025-06-24T13:26:54Z",
    "updatedAt": "2025-06-24T13:29:37Z",
    "interactions": {
      "stars": 0,
      "forks": 0
    }
  },
  {
    "title": "WhoDidWhat",
    "description": "Rajapeth Bridge Design Project This is a bridge project over the Purna River in Amravati. It includes:  G+1 span continuous T-beam system MIDAS Civil model and calculations Hand calculations for deck slab and pier GAD, reinforcement details in CAD Structure",
    "source": "https://github.com/shubhamjha2510/WhoDidWhat",
    "demo": "https://www.google.com",
    "language": "HTML",
    "platform": "github",
    "createdAt": "2024-11-29T17:44:17Z",
    "updatedAt": "2025-06-24T15:05:29Z",
    "interactions": {
      "stars": 0,
      "forks": 0
    }
  }
]